otel_tracer/__init__.py
otel_tracer/tracing/__init__.py
otel_tracer/tracing/tracer.py
otl_tracer-0.0.2.dist-info/METADATA
otl_tracer-0.0.2.dist-info/WHEEL
otl_tracer-0.0.2.dist-info/top_level.txt
otl_tracer-0.0.2.dist-info/RECORD
